{"start":"2020-06-20T22:59:04.595Z","end":"2020-06-20T22:59:12.984Z","capabilities":{"maxInstances":5,"browserName":"chrome"},"host":"127.0.0.1","port":4444,"baseUrl":"http://www.webdriveruniversity.com/","framework":"mocha","mochaOpts":{"timeout":99999999,"ui":"bdd"},"suites":[{"name":"Test whether hidden elements exist","duration":0,"start":"2020-06-20T22:59:09.508Z","tests":[],"hooks":[]},{"name":"Test whether hidden elements exist","duration":2632,"start":"2020-06-20T22:59:09.508Z","end":"2020-06-20T22:59:12.140Z","tests":[{"name":"Set to display: none; Still exists in DOM return true","start":"2020-06-20T22:59:09.508Z","end":"2020-06-20T22:59:11.265Z","duration":1757,"state":"pass"},{"name":"Set to visibility: hidden; Still exists in DOM return true","start":"2020-06-20T22:59:11.265Z","end":"2020-06-20T22:59:11.337Z","duration":72,"state":"pass"},{"name":"Set to opacity: 0; Still exists in DOM return true","start":"2020-06-20T22:59:11.338Z","end":"2020-06-20T22:59:11.405Z","duration":67,"state":"pass"},{"name":"Header text always visible & should return true","start":"2020-06-20T22:59:11.406Z","end":"2020-06-20T22:59:11.482Z","duration":76,"state":"pass"},{"name":"No such element should return false","start":"2020-06-20T22:59:11.482Z","end":"2020-06-20T22:59:11.565Z","duration":83,"state":"pass"},{"name":"Should be false, set to display: none","start":"2020-06-20T22:59:11.565Z","end":"2020-06-20T22:59:11.640Z","duration":75,"state":"pass"},{"name":"Should be false, set to visibility: hidden","start":"2020-06-20T22:59:11.641Z","end":"2020-06-20T22:59:11.720Z","duration":79,"state":"pass"},{"name":"Should be false, set to opacity: 0","start":"2020-06-20T22:59:11.720Z","end":"2020-06-20T22:59:11.797Z","duration":77,"state":"pass"},{"name":"Header text always visible & should return true","start":"2020-06-20T22:59:11.797Z","end":"2020-06-20T22:59:11.884Z","duration":87,"state":"pass"},{"name":"No such element should return false","start":"2020-06-20T22:59:11.884Z","end":"2020-06-20T22:59:11.943Z","duration":59,"state":"pass"},{"name":"should not be visible within current viewport","start":"2020-06-20T22:59:11.944Z","end":"2020-06-20T22:59:12.032Z","duration":88,"state":"pass"},{"name":"should be visible within current viewport","start":"2020-06-20T22:59:12.032Z","end":"2020-06-20T22:59:12.139Z","duration":107,"state":"pass"}],"hooks":[{"start":"2020-06-20T22:59:09.509Z","end":"2020-06-20T22:59:11.239Z","duration":1730,"title":"\"before each\" hook","associatedSuite":"Test whether hidden elements exist","associatedTest":"Set to display: none; Still exists in DOM return true"},{"start":"2020-06-20T22:59:11.240Z","end":"2020-06-20T22:59:11.240Z","duration":0,"title":"\"before each\" hook","associatedSuite":"Test whether hidden elements exist","associatedTest":"Set to display: none; Still exists in DOM return true"},{"start":"2020-06-20T22:59:11.265Z","end":"2020-06-20T22:59:11.265Z","duration":0,"title":"\"after each\" hook","associatedSuite":"Test whether hidden elements exist","associatedTest":"Set to display: none; Still exists in DOM return true"},{"start":"2020-06-20T22:59:11.266Z","end":"2020-06-20T22:59:11.322Z","duration":56,"title":"\"before each\" hook","associatedSuite":"Test whether hidden elements exist","associatedTest":"Set to visibility: hidden; Still exists in DOM return true"},{"start":"2020-06-20T22:59:11.322Z","end":"2020-06-20T22:59:11.322Z","duration":0,"title":"\"before each\" hook","associatedSuite":"Test whether hidden elements exist","associatedTest":"Set to visibility: hidden; Still exists in DOM return true"},{"start":"2020-06-20T22:59:11.338Z","end":"2020-06-20T22:59:11.338Z","duration":0,"title":"\"after each\" hook","associatedSuite":"Test whether hidden elements exist","associatedTest":"Set to visibility: hidden; Still exists in DOM return true"},{"start":"2020-06-20T22:59:11.338Z","end":"2020-06-20T22:59:11.390Z","duration":52,"title":"\"before each\" hook","associatedSuite":"Test whether hidden elements exist","associatedTest":"Set to opacity: 0; Still exists in DOM return true"},{"start":"2020-06-20T22:59:11.390Z","end":"2020-06-20T22:59:11.390Z","duration":0,"title":"\"before each\" hook","associatedSuite":"Test whether hidden elements exist","associatedTest":"Set to opacity: 0; Still exists in DOM return true"},{"start":"2020-06-20T22:59:11.406Z","end":"2020-06-20T22:59:11.406Z","duration":0,"title":"\"after each\" hook","associatedSuite":"Test whether hidden elements exist","associatedTest":"Set to opacity: 0; Still exists in DOM return true"},{"start":"2020-06-20T22:59:11.406Z","end":"2020-06-20T22:59:11.468Z","duration":62,"title":"\"before each\" hook","associatedSuite":"Test whether hidden elements exist","associatedTest":"Header text always visible & should return true"},{"start":"2020-06-20T22:59:11.468Z","end":"2020-06-20T22:59:11.468Z","duration":0,"title":"\"before each\" hook","associatedSuite":"Test whether hidden elements exist","associatedTest":"Header text always visible & should return true"},{"start":"2020-06-20T22:59:11.482Z","end":"2020-06-20T22:59:11.482Z","duration":0,"title":"\"after each\" hook","associatedSuite":"Test whether hidden elements exist","associatedTest":"Header text always visible & should return true"},{"start":"2020-06-20T22:59:11.482Z","end":"2020-06-20T22:59:11.545Z","duration":63,"title":"\"before each\" hook","associatedSuite":"Test whether hidden elements exist","associatedTest":"No such element should return false"},{"start":"2020-06-20T22:59:11.545Z","end":"2020-06-20T22:59:11.545Z","duration":0,"title":"\"before each\" hook","associatedSuite":"Test whether hidden elements exist","associatedTest":"No such element should return false"},{"start":"2020-06-20T22:59:11.565Z","end":"2020-06-20T22:59:11.565Z","duration":0,"title":"\"after each\" hook","associatedSuite":"Test whether hidden elements exist","associatedTest":"No such element should return false"},{"start":"2020-06-20T22:59:11.565Z","end":"2020-06-20T22:59:11.617Z","duration":52,"title":"\"before each\" hook","associatedSuite":"Test whether hidden elements exist","associatedTest":"Should be false, set to display: none"},{"start":"2020-06-20T22:59:11.617Z","end":"2020-06-20T22:59:11.617Z","duration":0,"title":"\"before each\" hook","associatedSuite":"Test whether hidden elements exist","associatedTest":"Should be false, set to display: none"},{"start":"2020-06-20T22:59:11.641Z","end":"2020-06-20T22:59:11.641Z","duration":0,"title":"\"after each\" hook","associatedSuite":"Test whether hidden elements exist","associatedTest":"Should be false, set to display: none"},{"start":"2020-06-20T22:59:11.641Z","end":"2020-06-20T22:59:11.696Z","duration":55,"title":"\"before each\" hook","associatedSuite":"Test whether hidden elements exist","associatedTest":"Should be false, set to visibility: hidden"},{"start":"2020-06-20T22:59:11.696Z","end":"2020-06-20T22:59:11.696Z","duration":0,"title":"\"before each\" hook","associatedSuite":"Test whether hidden elements exist","associatedTest":"Should be false, set to visibility: hidden"},{"start":"2020-06-20T22:59:11.720Z","end":"2020-06-20T22:59:11.720Z","duration":0,"title":"\"after each\" hook","associatedSuite":"Test whether hidden elements exist","associatedTest":"Should be false, set to visibility: hidden"},{"start":"2020-06-20T22:59:11.720Z","end":"2020-06-20T22:59:11.772Z","duration":52,"title":"\"before each\" hook","associatedSuite":"Test whether hidden elements exist","associatedTest":"Should be false, set to opacity: 0"},{"start":"2020-06-20T22:59:11.772Z","end":"2020-06-20T22:59:11.772Z","duration":0,"title":"\"before each\" hook","associatedSuite":"Test whether hidden elements exist","associatedTest":"Should be false, set to opacity: 0"},{"start":"2020-06-20T22:59:11.797Z","end":"2020-06-20T22:59:11.797Z","duration":0,"title":"\"after each\" hook","associatedSuite":"Test whether hidden elements exist","associatedTest":"Should be false, set to opacity: 0"},{"start":"2020-06-20T22:59:11.797Z","end":"2020-06-20T22:59:11.858Z","duration":61,"title":"\"before each\" hook","associatedSuite":"Test whether hidden elements exist","associatedTest":"Header text always visible & should return true"},{"start":"2020-06-20T22:59:11.858Z","end":"2020-06-20T22:59:11.858Z","duration":0,"title":"\"before each\" hook","associatedSuite":"Test whether hidden elements exist","associatedTest":"Header text always visible & should return true"},{"start":"2020-06-20T22:59:11.884Z","end":"2020-06-20T22:59:11.884Z","duration":0,"title":"\"after each\" hook","associatedSuite":"Test whether hidden elements exist","associatedTest":"Header text always visible & should return true"},{"start":"2020-06-20T22:59:11.884Z","end":"2020-06-20T22:59:11.931Z","duration":47,"title":"\"before each\" hook","associatedSuite":"Test whether hidden elements exist","associatedTest":"No such element should return false"},{"start":"2020-06-20T22:59:11.931Z","end":"2020-06-20T22:59:11.931Z","duration":0,"title":"\"before each\" hook","associatedSuite":"Test whether hidden elements exist","associatedTest":"No such element should return false"},{"start":"2020-06-20T22:59:11.944Z","end":"2020-06-20T22:59:11.944Z","duration":0,"title":"\"after each\" hook","associatedSuite":"Test whether hidden elements exist","associatedTest":"No such element should return false"},{"start":"2020-06-20T22:59:11.944Z","end":"2020-06-20T22:59:11.991Z","duration":47,"title":"\"before each\" hook","associatedSuite":"Test whether hidden elements exist","associatedTest":"should not be visible within current viewport"},{"start":"2020-06-20T22:59:11.991Z","end":"2020-06-20T22:59:11.991Z","duration":0,"title":"\"before each\" hook","associatedSuite":"Test whether hidden elements exist","associatedTest":"should not be visible within current viewport"},{"start":"2020-06-20T22:59:12.032Z","end":"2020-06-20T22:59:12.032Z","duration":0,"title":"\"after each\" hook","associatedSuite":"Test whether hidden elements exist","associatedTest":"should not be visible within current viewport"},{"start":"2020-06-20T22:59:12.032Z","end":"2020-06-20T22:59:12.114Z","duration":82,"title":"\"before each\" hook","associatedSuite":"Test whether hidden elements exist","associatedTest":"should be visible within current viewport"},{"start":"2020-06-20T22:59:12.114Z","end":"2020-06-20T22:59:12.114Z","duration":0,"title":"\"before each\" hook","associatedSuite":"Test whether hidden elements exist","associatedTest":"should be visible within current viewport"},{"start":"2020-06-20T22:59:12.140Z","end":"2020-06-20T22:59:12.140Z","duration":0,"title":"\"after each\" hook","associatedSuite":"Test whether hidden elements exist","associatedTest":"should be visible within current viewport"},{"start":"2020-06-20T22:59:12.200Z","end":"2020-06-20T22:59:12.200Z","duration":0,"title":"\"after all\" hook","associatedSuite":"Test whether hidden elements exist"}]}],"state":{"passed":12,"failed":0,"skipped":0}}